pyntegrals/__init__.py
pyntegrals/integrals.py
pyntegrals-1.0.0.dist-info/LICENSE
pyntegrals-1.0.0.dist-info/METADATA
pyntegrals-1.0.0.dist-info/WHEEL
pyntegrals-1.0.0.dist-info/top_level.txt
pyntegrals-1.0.0.dist-info/RECORD
