Metadata-Version: 2.1
Name: pyntegrals
Version: 1.0.0
Summary: A tool for calculating definite integrals over a 2D polygonal domain
Author-email: quacksort <quacksort@gmail.com>
License: GNU AFFERO GENERAL PUBLIC LICENSE
Project-URL: Homepage, https://github.com/quacksort/pyntegrals
Keywords: integral,polygon,double integral
Classifier: License :: OSI Approved :: GNU Affero General Public License v3
Classifier: Programming Language :: Python
Classifier: Programming Language :: Python :: 3
Requires-Python: >=3.9
License-File: LICENSE
Requires-Dist: numpy
Requires-Dist: tripy
Requires-Dist: scipy
Requires-Dist: shapely
